KFS/__init__.py
KFS/config.py
KFS/convert_to_SI.py
KFS/dropbox.py
KFS/exceptions.py
KFS/fstr.py
KFS/licence.md
KFS/log.py
KFS/math.py
KFS/media.py
KFS/sleep.py
kfs-1.1.1.dist-info/METADATA
kfs-1.1.1.dist-info/WHEEL
kfs-1.1.1.dist-info/RECORD
