Metadata-Version: 2.1
Name: KFS
Version: 1.1.1
Summary: a collection of miscellaneous functions
Home-page: https://github.com/9-FS/2022-04-07-KFS-Library-Python
License: MIT
Author: 9FS
Author-email: pray4spam@googlemail.com
Requires-Python: >=3.11,<4.0
Classifier: License :: OSI Approved :: MIT License
Classifier: Programming Language :: Python :: 3
Classifier: Programming Language :: Python :: 3.11
Requires-Dist: colorama (>=0.4.6,<0.5.0)
Requires-Dist: dropbox (>=11.36.0,<12.0.0)
Requires-Dist: lxml (>=4.9.2,<5.0.0)
Requires-Dist: pillow (>=9.4.0,<10.0.0)
Requires-Dist: requests (>=2.28.0,<3.0.0)
Project-URL: Repository, https://github.com/9-FS/2022-04-07-KFS-Library-Python
